{
  "id": 8369,
  "league": {
    "id": 27,
    "name": "World Cup 2026",
    "country": "International",
    "is_women": false,
    "current_season": {
      "id": 188,
      "name": "World Cup 2026",
      "year": 2026,
      "start_date": "2026-01-01",
      "end_date": "2026-12-31"
    }
  },
  "season": {
    "id": 188,
    "name": "World Cup 2026",
    "year": 2026
  },
  "home_team": "Spain",
  "away_team": "Austria",
  "home_team_obj": {
    "id": 475,
    "name": "Spain",
    "short_name": "Spain",
    "country": "Spain",
    "coach": {
      "name": "Luis De La Fuente",
      "shortName": "L. D. L. Fuente"
    },
    "venue": null
  },
  "away_team_obj": {
    "id": 483,
    "name": "Austria",
    "short_name": "Austria",
    "country": "Austria",
    "coach": {
      "name": "Ralf Rangnick",
      "shortName": "R. Rangnick"
    },
    "venue": {
      "id": 440,
      "name": "Ernst Happel Stadion",
      "city": "Vienna",
      "country": "Austria",
      "capacity": 50865
    }
  },
  "event_date": "2026-07-02T23:00:00+04:00",
  "round_number": 6,
  "round_name": "Round of 32",
  "group_name": null,
  "status": "notstarted",
  "home_score": null,
  "away_score": null,
  "home_score_ht": null,
  "away_score_ht": null,
  "current_minute": null,
  "period": "",
  "odds_home": 1.33,
  "odds_draw": 5.16,
  "odds_away": 9.62,
  "odds_over_15": 1.24,
  "odds_over_25": 1.78,
  "odds_over_35": 2.95,
  "odds_under_15": 3.82,
  "odds_under_25": 2.01,
  "odds_under_35": 1.38,
  "odds_btts_yes": 2.2,
  "odds_btts_no": 1.62,
  "actual_home_xg": null,
  "actual_away_xg": null,
  "home_xg_live": null,
  "away_xg_live": null,
  "penalty_shootout": null,
  "extra_time_score": null,
  "is_local_derby": false,
  "is_neutral_ground": null,
  "travel_distance_km": null,
  "weather_code": 3,
  "wind_speed": 13.8,
  "temperature_c": 25,
  "pitch_condition": null,
  "attendance": null,
  "referee": {
    "id": 2039,
    "name": "Glenn Nyberg",
    "country": "Sweden",
    "nationality_a3": "",
    "birthdate": null,
    "yellowCards": 1235,
    "redCards": 20,
    "career_games": 375,
    "career_yellow_cards": 1235,
    "career_red_cards": 20
  },
  "home_coach": {
    "id": 116,
    "name": "Luis De La Fuente",
    "short_name": "L. D. L. Fuente",
    "country": "Spain",
    "profile": "attacking",
    "preferred_formation": "4-2-3-1",
    "pressing_intensity": 0.5531225495115476,
    "defensive_line": "mid",
    "top_styles": [
      "tiki_taka",
      "positional"
    ]
  },
  "away_coach": {
    "id": 104,
    "name": "Ralf Rangnick",
    "short_name": "R. Rangnick",
    "country": "Germany",
    "profile": "attacking",
    "preferred_formation": "4-2-3-1",
    "pressing_intensity": 0.5554813200380221,
    "defensive_line": "low",
    "top_styles": [
      "tiki_taka",
      "territory"
    ]
  },
  "unavailable_players": null,
  "venue": {
    "id": 1180,
    "name": "SoFi Stadium",
    "city": "Inglewood",
    "country": "USA",
    "capacity": 70242,
    "latitude": 33.953536,
    "longitude": -118.338734,
    "pitch_x": 105,
    "pitch_y": 68,
    "built_year": null
  },
  "live_stats": null,
  "jerseys": {
    "away": {
      "GK": {
        "base": "d7e768",
        "real": true,
        "type": "short_sleeves",
        "number": "111010",
        "sleeve": "d6e76e"
      },
      "player": {
        "base": "ff0000",
        "real": true,
        "type": "short_sleeves",
        "number": "ffffff",
        "sleeve": "de3631",
        "sleevelong": "000000"
      }
    },
    "home": {
      "GK": {
        "base": "edd542",
        "real": true,
        "type": "long_sleeves",
        "number": "2e3130",
        "sleeve": "1c201e"
      },
      "player": {
        "base": "f94046",
        "real": true,
        "type": "short_sleeves",
        "number": "fddc30",
        "sleeve": "353c69",
        "sleevelong": "343f6e"
      }
    }
  },
  "funfacts": [
    {
      "type_id": 2,
      "sentence": "Austria haven't won any of their last 5 games against Spain."
    },
    {
      "type_id": 1,
      "sentence": "Spain haven't lost in their last 13 games."
    },
    {
      "type_id": 6,
      "sentence": "Austria has previously won 4 of 6 matches against Spain."
    }
  ],
  "sr_stats": null,
  "ai_preview": {
    "text": "**Spain's attack meets Austria's leaky defense** — this could get spicy fast. 🔥 La Roja are rolling with 3 wins in their last 5, while Austria's been a bit all over the map (3W-1D-1L), including a surprise 3-3 draw with Algeria.\n\nSpain miss **L. Yamal**, **N. Williams**, and **Y. Pino** through injury, but they've still got serious firepower with **Rodri** orchestrating midfield and **B. Iglesias** leading the line. Austria have to contain that creative spark — **M. Sabitzer** and **N. Seiwald** will need to be all business in the middle.\n\nKey storylines:\n\n- **Spain's midfield dominance**: **Pedri**, **A. Baena**, and **Rodri** vs Austria's two-man shield could be the entire match right here\n- **Austria's fragility in defense**: They've leaked goals in bunches lately; **Spain's front four** will fancy their chances\n- **Depth matters**: Austria have talent, but Spain's injury list is shorter than the gap in form between these sides\n\nExpected lineups:\n\n- **Spain**: U. Simón, A. Laporte, P. Cubarsí, M. Cucurella, M. Llorente, A. Baena, Pedri, M. Oyarzabal, Rodri, F. Torres, B. Iglesias\n- **Austria**: A. Schlager, K. Laimer, P. Lienhart, K. Danso, S. Posch, M. Sabitzer, N. Seiwald, C. Baumgartner, X. Schlager, M. Gregoritsch, S. Kalajdžić\n\nBest picks:\n\n- **Total Goals 1.5**: Over 1.5 goals\n\nPrediction:\n\n**Spain 2–1 Austria**. Spain's edge in midfield and form is too much; Austria pull one back but don't have the firepower to level. ⚪",
    "generated_at": "2026-07-01T19:45:21.618049+00:00"
  },
  "live_websocket": true,
  "home_form": {
    "calculated_at": "2026-07-01",
    "matches_played": 5,
    "form_string": "WWDLD",
    "wins": 2,
    "draws": 2,
    "losses": 1,
    "points_last_n": 8,
    "goals_scored_last_n": 7,
    "goals_conceded_last_n": 3,
    "avg_xg": 2.0088,
    "avg_xg_conceded": 0.21233333333333335,
    "avg_shots": 18.333333333333332,
    "avg_shots_on_target": 5.333333333333333,
    "avg_key_passes": 14.0,
    "goal_conversion_rate": 1.1615558210540289,
    "defensive_efficiency": -3.7095761381475665,
    "clean_sheets": 3,
    "avg_pass_accuracy": 90.84581055290083,
    "duel_win_rate": 0.4898785425101215,
    "aerial_win_rate": 0.7258064516129032,
    "avg_fouls": 11.333333333333334,
    "avg_yellow_cards": 0.6666666666666666,
    "home_ppg": 1.8,
    "away_ppg": 2.0,
    "home_goals_scored": 14,
    "home_goals_conceded": 3,
    "away_goals_scored": 9,
    "away_goals_conceded": 5,
    "avg_team_rating": 7.139444444444444
  },
  "away_form": {
    "calculated_at": "2026-07-01",
    "matches_played": 3,
    "form_string": "DLW",
    "wins": 1,
    "draws": 1,
    "losses": 1,
    "points_last_n": 4,
    "goals_scored_last_n": 6,
    "goals_conceded_last_n": 6,
    "avg_xg": 1.1992666666666667,
    "avg_xg_conceded": 1.6033666666666668,
    "avg_shots": 9.0,
    "avg_shots_on_target": 2.6666666666666665,
    "avg_key_passes": 6.0,
    "goal_conversion_rate": 1.667685807993774,
    "defensive_efficiency": -0.24737531444252703,
    "clean_sheets": 0,
    "avg_pass_accuracy": 85.72967310828858,
    "duel_win_rate": 0.46311475409836067,
    "aerial_win_rate": 0.640625,
    "avg_fouls": 10.666666666666666,
    "avg_yellow_cards": 1.3333333333333333,
    "home_ppg": 3.0,
    "away_ppg": 0.5,
    "home_goals_scored": 3,
    "home_goals_conceded": 1,
    "away_goals_scored": 3,
    "away_goals_conceded": 5,
    "avg_team_rating": 6.645833333333333
  },
  "head_to_head": null,
  "lineups": null,
  "social": []
}